bisanggu
